hmstime.py
hmstime-1.0.dist-info/LICENSE
hmstime-1.0.dist-info/METADATA
hmstime-1.0.dist-info/WHEEL
hmstime-1.0.dist-info/top_level.txt
hmstime-1.0.dist-info/zip-safe
hmstime-1.0.dist-info/RECORD
