Metadata-Version: 2.1
Name: hmstime
Version: 1.0
Summary: time format converter
Home-page: https://github.com/koodaamo/hmstime
Author: Petri Savolainen
Author-email: petri@koodaamo.fi
License: GPLv2
Keywords: timedelta,time,human readable
Platform: UNKNOWN
Classifier: License :: OSI Approved :: GNU General Public License v2 (GPLv2)
Classifier: Programming Language :: Python :: 3
Classifier: Programming Language :: Python :: 3.10
License-File: LICENSE
